nitro.cpython-312-darwin.so
nitro.pyi
nitro_sim-0.1.0.dist-info/RECORD
nitro_sim-0.1.0.dist-info/WHEEL
nitro_sim-0.1.0.dist-info/METADATA
src/pettingzoo_env.py
src/nitro.pyi
src/bindings.cpp
