Metadata-Version: 2.2
Name: nitro-sim
Version: 0.1.0
Summary: Python bindings for RocketSim - Rocket League physics simulation
Author-Email: Aaron Davis <52721338+2ToTheNthPower@users.noreply.github.com>
Requires-Python: >=3.12
Requires-Dist: gymnasium>=1.2.2
Requires-Dist: numpy>=2.3.5
Provides-Extra: test
Requires-Dist: pytest>=7.0.0; extra == "test"
